secure_file_storage/__init__.py
secure_file_storage/main.py
secure_file_storage/version.py
secure_file_storage/src/__init__.py
secure_file_storage/src/auth.py
secure_file_storage/src/encryption.py
secure_file_storage/src/logger.py
secure_file_storage/src/setup_env.py
secure_file_storage/src/utils.py
secure_file_storage/src/routes/__init__.py
secure_file_storage/src/routes/auth_routes.py
secure_file_storage/src/routes/common_routes.py
secure_file_storage/src/routes/storage_routes.py
secure_file_storage_milosz275-0.3.0.dist-info/licenses/LICENSE
tests/test_auth.py
tests/test_encryption.py
secure_file_storage_milosz275-0.3.0.dist-info/METADATA
secure_file_storage_milosz275-0.3.0.dist-info/WHEEL
secure_file_storage_milosz275-0.3.0.dist-info/entry_points.txt
secure_file_storage_milosz275-0.3.0.dist-info/top_level.txt
secure_file_storage_milosz275-0.3.0.dist-info/RECORD
