Metadata-Version: 2.4
Name: secure-file-storage-milosz275
Version: 0.3.0
Summary: Secure File Storage is a secure, encrypted file storage solution developed in Python. It combines strong encryption, modular architecture, logging and basic access control.
Author-email: milosz275 <miloszmaculewicz@gmail.com>
Project-URL: Homepage, https://github.com/milosz275/secure-file-storage
Project-URL: Issues, https://github.com/milosz275/secure-file-storage/issues
Classifier: Programming Language :: Python :: 3
Classifier: License :: OSI Approved :: MIT License
Classifier: Operating System :: OS Independent
Requires-Python: >=3.11
License-File: LICENSE
Dynamic: license-file
